{
    "name": "",
    "description": "",
    "created_by": "system",
    "modified_by": "system",
    "cts": "2021-07-02T11:30:52.497603",
    "uts": "2021-07-05T08:47:49.712660",
    "_XpmsObjectMixin__type": "ModelComparison",
    "_XpmsObjectMixin__api_version": "10.0",
    "model_id": "6ac5fabb-b56f-405c-947d-39fc4d4e74b0",
    "model_type": "classification",
    "scoring_metric": "accuracy",
    "baseline_version": "",
    "cutoff": {
        "scores": {
            "accuracy": 0.9046867114880593,
            "precision": 0.998493957115461,
            "recall": 0.9046867114880593,
            "f1": 0.9484720938994204
        },
        "classes": {
            "0": {
                "precision": 0.015800974953773743,
                "recall": 1.0,
                "f1-score": 0.031110375641237795,
                "support": 94
            },
            "1": {
                "precision": 1.0,
                "recall": 0.9045406374826771,
                "f1-score": 0.9498780122415785,
                "support": 61335
            }
        }
    },
    "model_config_id": "fc079056-9770-49ed-9133-c4cd50f5f8d0",
    "is_deleted": false,
    "model_comparisons": {
        "d4020ef2-784c-4e0e-8e10-f248c142f190": {
            "840e8640-a108-47c2-ba89-c0869ed284f6": {
                "classes": {
                    "0": {
                        "precision": 0.015800974953773743,
                        "recall": 1.0,
                        "f1-score": 0.031110375641237795,
                        "support": 94
                    },
                    "1": {
                        "precision": 1.0,
                        "recall": 0.9045406374826771,
                        "f1-score": 0.9498780122415785,
                        "support": 61335
                    }
                },
                "scores": {
                    "accuracy": 0.9046867114880593,
                    "precision": 0.998493957115461,
                    "recall": 0.9046867114880593,
                    "f1": 0.9484720938994204
                },
                "is_recommended": true,
                "is_cutoff_passed": true
            }
        }
    }
}